quipubase/__init__.py
quipubase/_base.py
quipubase/blobs.py
quipubase/collections.py
quipubase/objects.py
quipubase/orm.py
quipubase/py.typed
quipubase/query.py
quipubase/vector.py
quipubase-0.0.5.dist-info/METADATA
quipubase-0.0.5.dist-info/WHEEL
quipubase-0.0.5.dist-info/top_level.txt
quipubase-0.0.5.dist-info/RECORD
