Metadata-Version: 2.4
Name: quipubase
Version: 0.0.5
Summary: Quipubase Python Client
Requires-Python: >=3.10
Requires-Dist: pydantic
Requires-Dist: httpx
Requires-Dist: loguru>=0.7.3
Requires-Dist: openai>=1.98.0
Requires-Dist: rustid>=0.0.2
